pytray/__init__.py
pytray/aiothreads.py
pytray/futures.py
pytray/obj_load.py
pytray/pretty.py
pytray/tree.py
pytray/version.py
pytray/weakdict.py
pytray-0.3.4.dist-info/LICENSE
pytray-0.3.4.dist-info/METADATA
pytray-0.3.4.dist-info/WHEEL
pytray-0.3.4.dist-info/top_level.txt
pytray-0.3.4.dist-info/RECORD
